pyexpress/__init__.py
pyexpress/fileisnotincurrentdirectoryerror.py
pyexpress/httpconstants.py
pyexpress/httpnext.py
pyexpress/httprequest.py
pyexpress/httpresponse.py
pyexpress/httpresponseclosederror.py
pyexpress/httpserverhelper.py
pyexpress-0.1.0a5.dist-info/DESCRIPTION.rst
pyexpress-0.1.0a5.dist-info/METADATA
pyexpress-0.1.0a5.dist-info/RECORD
pyexpress-0.1.0a5.dist-info/WHEEL
pyexpress-0.1.0a5.dist-info/metadata.json
pyexpress-0.1.0a5.dist-info/top_level.txt
