Metadata-Version: 2.0
Name: pyexpress
Version: 0.1.0a5
Summary: A HTTP server framework
Home-page: https://github.com/drubay/pyexpress
Author: sdrubay
Author-email: turtlepower@free.fr
License: MIT
Keywords: http server express
Platform: UNKNOWN
